dxldomaintoolsservice/__init__.py
dxldomaintoolsservice/__main__.py
dxldomaintoolsservice/_version.py
dxldomaintoolsservice/app.py
dxldomaintoolsservice/requesthandlers.py
dxldomaintoolsservice/_config/__init__.py
dxldomaintoolsservice/_config/app/__init__.py
dxldomaintoolsservice/_config/app/dxlclient.config
dxldomaintoolsservice/_config/app/dxldomaintoolsservice.config
dxldomaintoolsservice/_config/app/logging.config
dxldomaintoolsservice/_config/sample/__init__.py
dxldomaintoolsservice/_config/sample/dxlclient.config
dxldomaintoolsservice-0.2.1.dist-info/LICENSE
dxldomaintoolsservice-0.2.1.dist-info/METADATA
dxldomaintoolsservice-0.2.1.dist-info/WHEEL
dxldomaintoolsservice-0.2.1.dist-info/top_level.txt
dxldomaintoolsservice-0.2.1.dist-info/RECORD
